slmaker/__init__.py
slmaker/greetings.py
salutations_maker-0.0.4.dist-info/METADATA
salutations_maker-0.0.4.dist-info/WHEEL
salutations_maker-0.0.4.dist-info/top_level.txt
salutations_maker-0.0.4.dist-info/RECORD
