Metadata-Version: 2.1
Name: salutations-maker
Version: 0.0.4
Summary: A package to say hello
Home-page: UNKNOWN
Author: Nathan Derave
Author-email: nathan.derave@dataminde.be
License: UNKNOWN
Platform: UNKNOWN
Requires-Python: >=3.6
Requires-Dist: pandas (>=1.1.0)
Requires-Dist: scikit-learn (>=0.23.1)
Provides-Extra: dev
Requires-Dist: pytest ; extra == 'dev'
Requires-Dist: flake8 ; extra == 'dev'
Requires-Dist: tox ; extra == 'dev'
Requires-Dist: twine ; extra == 'dev'
